README.md
setup.cfg
setup.py
PyEyeTrack.egg-info/PKG-INFO
PyEyeTrack.egg-info/SOURCES.txt
PyEyeTrack.egg-info/dependency_links.txt
PyEyeTrack.egg-info/requires.txt
PyEyeTrack.egg-info/top_level.txt
pyEyeTrack/DataHandling.py
pyEyeTrack/PyEyeTrackRunnerClass.py
pyEyeTrack/__init__.py
pyEyeTrack/AudioVideoRecording/AudioRecordingClass.py
pyEyeTrack/AudioVideoRecording/VideoRecordingClass.py
pyEyeTrack/AudioVideoRecording/__init__.py
pyEyeTrack/EyeTracking/AbstractEyeTrackingClass.py
pyEyeTrack/EyeTracking/BlinkingClass.py
pyEyeTrack/EyeTracking/PupilBlinkingClass.py
pyEyeTrack/EyeTracking/PupilTrackingClass.py
pyEyeTrack/EyeTracking/__init__.py
pyEyeTrack/EyeTracking/test.py